EwApi/__init__.py
easy_whitelist/__init__.py
easy_whitelist/__main__.py
easy_whitelist/_core.py
easy_whitelist/hello.txt
easy_whitelist/py.typed
easy_whitelist/config/__init__.py
easy_whitelist/config/arg.py
easy_whitelist/config/log.py
easy_whitelist/ip_detector/__init__.py
easy_whitelist/ip_detector/detectors.py
easy_whitelist/ip_detector/utils.py
easy_whitelist/tcloud/__init__.py
easy_whitelist/tcloud/client.py
easy_whitelist/tcloud/core.py
easy_whitelist/tcloud/ls_template.py
easy_whitelist/tcloud/template.py
easy_whitelist-1.0.103.dist-info/licenses/LICENSE
easy_whitelist-1.0.103.dist-info/METADATA
easy_whitelist-1.0.103.dist-info/WHEEL
easy_whitelist-1.0.103.dist-info/entry_points.txt
easy_whitelist-1.0.103.dist-info/top_level.txt
easy_whitelist-1.0.103.dist-info/RECORD
