Metadata-Version: 2.4
Name: easy_whitelist
Version: 1.0.103
Summary: A smart tool that detects the local Internet IP address and automatically updates the local Internet IP address to the cloud security group whitelist.
Home-page: https://github.com/qiqilelebaobao/easy_whitelist
Author: qiqilelebaobao
Author-email: qiqilelebaobao@163.com
License: Apache License 2.0
Keywords: whitelist,security-groups,alibaba-cloud,tencent-cloud,security-tools
Classifier: Programming Language :: Python :: 3
Classifier: Programming Language :: Python :: 3 :: Only
Classifier: Programming Language :: Python :: 3.8
Classifier: Programming Language :: Python :: 3.9
Classifier: Programming Language :: Python :: 3.10
Classifier: Programming Language :: Python :: 3.11
Classifier: Programming Language :: Python :: 3.12
Classifier: Operating System :: OS Independent
Classifier: Topic :: Security
Classifier: Topic :: System :: Networking
Classifier: Intended Audience :: System Administrators
Requires-Python: >=3.8
License-File: LICENSE
Requires-Dist: requests
Requires-Dist: tencentcloud-sdk-python
Provides-Extra: cli
Requires-Dist: rich; extra == "cli"
Requires-Dist: click>=5.0; extra == "cli"
Dynamic: author
Dynamic: author-email
Dynamic: classifier
Dynamic: description
Dynamic: description-content-type
Dynamic: home-page
Dynamic: keywords
Dynamic: license
Dynamic: license-file
Dynamic: provides-extra
Dynamic: requires-dist
Dynamic: requires-python
Dynamic: summary
